client/__init__.py
client/add_contact.py
client/database.py
client/del_contact.py
client/main_window.py
client/main_window_conv.py
client/start_dialog.py
client/transport.py
common/__init__.py
common/decorators.py
common/descriptors.py
common/errors.py
common/metaclasses.py
common/utils.py
common/variables.py
log/__init__.py
log/client_log_config.py
message_client_korobanov-0.0.5.dist-info/METADATA
message_client_korobanov-0.0.5.dist-info/WHEEL
message_client_korobanov-0.0.5.dist-info/top_level.txt
message_client_korobanov-0.0.5.dist-info/RECORD
