Metadata-Version: 2.1
Name: message-client-korobanov
Version: 0.0.5
Summary: message_client_korobanov_project
Author: George Korobanov
Author-email: georgekorob@gmail.com
Requires-Dist: PyQt5
Requires-Dist: sqlalchemy
Requires-Dist: pycryptodome
Requires-Dist: pycryptodomex
